{
    "camera": {
        "height": 164.0,
        "width": 229.0,
        "x": 0.0,
        "y": 0.0,
        "zoom": 0.9090909361839294
    },
    "entities": [
        {
            "type": "awesomeface",
            "x": -56.0,
            "y": 40.0
        },
        {
            "type": "awesomeface",
            "x": -56.0,
            "y": 24.0
        },
        {
            "type": "awesomeface",
            "x": -56.0,
            "y": 8.0
        },
        {
            "type": "awesomeface",
            "x": -56.0,
            "y": -8.0
        },
        {
            "type": "awesomeface",
            "x": -40.0,
            "y": -8.0
        },
        {
            "type": "awesomeface",
            "x": -24.0,
            "y": -8.0
        },
        {
            "type": "awesomeface",
            "x": -24.0,
            "y": 8.0
        },
        {
            "type": "awesomeface",
            "x": -8.0,
            "y": 8.0
        },
        {
            "type": "awesomeface",
            "x": -8.0,
            "y": 24.0
        },
        {
            "type": "awesomeface",
            "x": -8.0,
            "y": 40.0
        },
        {
            "type": "awesomeface",
            "x": -24.0,
            "y": 24.0
        },
        {
            "type": "awesomeface",
            "x": -24.0,
            "y": -24.0
        },
        {
            "type": "awesomeface",
            "x": 8.0,
            "y": 24.0
        },
        {
            "type": "awesomeface",
            "x": 8.0,
            "y": 40.0
        },
        {
            "type": "awesomeface",
            "x": 24.0,
            "y": 40.0
        },
        {
            "type": "awesomeface",
            "x": 40.0,
            "y": 40.0
        },
        {
            "type": "awesomeface",
            "x": 40.0,
            "y": 24.0
        },
        {
            "type": "awesomeface",
            "x": 40.0,
            "y": 8.0
        },
        {
            "type": "awesomeface",
            "x": 40.0,
            "y": -8.0
        },
        {
            "type": "awesomeface",
            "x": 56.0,
            "y": -8.0
        },
        {
            "type": "awesomeface",
            "x": 56.0,
            "y": -24.0
        },
        {
            "type": "awesomeface",
            "x": 56.0,
            "y": -40.0
        },
        {
            "type": "awesomeface",
            "x": 56.0,
            "y": -56.0
        },
        {
            "type": "awesomeface",
            "x": 72.0,
            "y": -56.0
        },
        {
            "type": "awesomeface",
            "x": 72.0,
            "y": -40.0
        },
        {
            "type": "awesomeface",
            "x": 72.0,
            "y": -24.0
        },
        {
            "type": "awesomeface",
            "x": 72.0,
            "y": -8.0
        },
        {
            "type": "awesomeface",
            "x": 72.0,
            "y": 8.0
        },
        {
            "type": "awesomeface",
            "x": 72.0,
            "y": 24.0
        },
        {
            "type": "awesomeface",
            "x": 88.0,
            "y": 24.0
        },
        {
            "type": "awesomeface",
            "x": 88.0,
            "y": 40.0
        },
        {
            "type": "awesomeface",
            "x": 88.0,
            "y": 56.0
        },
        {
            "type": "awesomeface",
            "x": 104.0,
            "y": 24.0
        },
        {
            "type": "awesomeface",
            "x": 104.0,
            "y": 8.0
        },
        {
            "type": "awesomeface",
            "x": 104.0,
            "y": -8.0
        },
        {
            "type": "awesomeface",
            "x": 104.0,
            "y": -24.0
        },
        {
            "type": "awesomeface",
            "x": 120.0,
            "y": 24.0
        },
        {
            "type": "awesomeface",
            "x": 120.0,
            "y": 40.0
        },
        {
            "type": "awesomeface",
            "x": 120.0,
            "y": 8.0
        },
        {
            "type": "awesomeface",
            "x": 104.0,
            "y": -40.0
        },
        {
            "type": "awesomeface",
            "x": 88.0,
            "y": -40.0
        },
        {
            "type": "awesomeface",
            "x": 88.0,
            "y": -56.0
        },
        {
            "type": "awesomeface",
            "x": 40.0,
            "y": -40.0
        },
        {
            "type": "awesomeface",
            "x": 24.0,
            "y": -40.0
        },
        {
            "type": "awesomeface",
            "x": 8.0,
            "y": -40.0
        },
        {
            "type": "awesomeface",
            "x": -8.0,
            "y": -40.0
        },
        {
            "type": "awesomeface",
            "x": -24.0,
            "y": -40.0
        }
    ],
    "grid": {
        "cellHeight": 16.0,
        "cellWidth": 16.0,
        "cols": 30,
        "rows": 20
    },
    "sceneName": "myScene.json"
}